{
  "研究背景": [],
  "研究目的": [
    "本文拟在对区域物流与区域经济关系进行理论分析的基础上，收集赣南原中央苏区13个地级城市的样本数据，对所构建的关系模型进行实证研究；通过运用SPSS19.0统计分析软件进行线性结构方程模型以及DEA分析、因子分析方法，得到区域物流与区域经济发展水平、区域物流与其构成指标以及区域经济发展水平与其构成指标的数量关系；通过分析区域物流与区域经济发展水平关系的线性结构方程模型，找出对区域物流和区域经济协调发展有着显著影响的指标，通过分析结果，对区域物流与区域经济协调发展提出对策。\n",
    "成为区域经济发展的重要组成部分。所以本文的研究意义如下：\n",
    "本文就是通过运用SPSS19.0统计分析软件进行线性结构方程模型以及DEA分析、因子分析方法，得到区域物流与区域经济发展水平、区域物流与其构成指标以及区域经济发展水平与其构成指标的数量关系。\n",
    "本文在研究区域物流与区域经济主的协调关系基础上，着重研究两者之间如何相互作用[5]。\n",
    "（4）赣南等原中央苏区是革命摇篮和苏区精神的主要发源地，深入了解促进赣南原中央苏区区域经济与区域物流协调发展，对赣南原中央苏区区域以及全国其它区域发展将有重大的理论价值和现实意义。\n"
  ],
  "研究综述": [],
  "理论介绍": [
    "首先介绍了区域物流的概念、特点；其次对区域经济的概念以及相关理论进行介绍；最后区域物流与区域经济的相互关系，介绍区域物流与区域经济之间的相互作用与影响。\n",
    "②梯度发展理论\n",
    "梯度发展是在不同区域空间上有规律的推进的一种经济技术发展理论。\n",
    "区域经济的发展理论梯度是我国在区域经济发展中制定决策、战略的重要思想。\n",
    "在区域经济中运用梯度发展理论，要考虑多方面形成因素：区域内各个地区之间存在技术方面的差距、市场体制、政府的政策等。\n",
    "所以，梯度理论就是在技术、人才等一些方面的差距，区域不同地区根据自身的条件来选择适合本地区发展的产业经济，然后根据梯度差异，区域之间进行在技术、科研、人才等方面的合作、分工共同推动区域经济的发展。\n",
    "③增长极理论\n",
    "增长极理论是以不平衡理论为基础的，在区域经济发展众多模式都是以不平衡体系为基础形成的。\n",
    "理论的扩展。\n",
    "而这主要作用对城市经济的快速发展、大城市位置布局以及对发展缓慢的城市的经济快速发展起着重要作用。\n",
    "④区域经济可持续发展理论\n",
    "⑤空间辐射理论\n",
    "根据不平衡发展理论，区域间发展不平衡是市场经济使区域经济发展的不均衡的辐射逐渐形成的。\n",
    "区域经济发展高水平的地区，该地区的技术、人才和资金就会向周边区域辐射与扩散，从而推动周边区域的经济发展而产生辐射效应。\n",
    "空间辐射理论在区域与区域经济关系发展与辐射作用方面提供了有力的科学依据，这样由高水平区域进行辐射促进落后区域经济快速稳定发展，更有利于提高区域经济水平。\n",
    "⑥区域协调发展理论\n",
    "区域协调发展理论可以缩小区域与区域在经济发展方面的差距，用来加快落后地区的经济发展，从而反作用于发达地区，为其提供有力的经济支撑。\n",
    "通过以上分析，可以得出一方面区域物流与区域经济之间存在着很强的依存关系，一方面区域物流与区域经济是相互作用，区域物流对区域经济发展的作用无可替代，同时能够提高生产领域和流通领域的运作效率，创造更多的经济效益，以此来提高区域市场的竞争能力[73]。\n",
    "建立模 型\n",
    "yF(x1, x2, x3,xi)是回归函数，ξ是随机误差，以此模型为基础，对赣南等原中央苏区江西省区域各地区物流量做出模型。\n"
  ],
  "研究假设": [
    "所以，规模效率DEA的有效的有6个，分别是兴国、瑞金、宁都、寻乌、信丰、安远。\n",
    "赣南苏区区域物流规模效率的平均值为0.841，但石城、广昌、黎川、上犹、崇义的规模都低于平均值，所以这五个地区物流发展潜力较大，如果扩大物流生产规模，可以增强区域的物流规模效率。\n",
    "3",
    "4",
    "3",
    "3",
    "4",
    "3",
    "本文拟采用KMO和Bartlett球度检验，检验结果如下表4-10所示，KMO的值为0.674，大于0.5，表示所搜集数据适合进行因子分析；Bartlett球度检验近似卡方值为122.264，自由度为45，检验的显著性概率为0.000，小于0.5，拒绝原假设，表示适合进行因子分析。\n",
    "3",
    "4",
    "所以，要积极改善赣南原中央苏区区域物流业发展不平衡的局面。\n",
    "3",
    "4",
    "3",
    "4",
    "4",
    "4",
    "3",
    "4",
    "4",
    "由表4-6系数显著性检验结果，从系数显著性检验来看，两个模型系数都是显著的，第二个模型比第一个模型增加了通车里程\\公里，增加该变量后，拟合优度显著增加，因此应该增加该变量。\n",
    "4",
    "4",
    "4",
    "4",
    "4",
    "4",
    "4",
    "4",
    "4",
    "4",
    "4",
    "4",
    "4",
    "3",
    "运用DEAP分析软件对表4-7数据进行计算，VRS（规模报酬可变）的计算结果如下表（4-8）\n",
    "3",
    "3",
    "量的信息，表明所选择的指标和所搜集到的数据能很好的反映13个城市的物流基本现状，从而为下面进行公因子提取提供了依据。\n",
    "4",
    "3",
    "4",
    "4",
    "4",
    "4",
    "由图可见，前2个公共因子的碎石图较为陡峭，第3个公共因子较陡峭，之后逐渐平缓，所以只需要提取前3个公共因子就能够反映大部分信息。\n",
    "3",
    "3",
    "3",
    "名情况，如表4-16所示：\n",
    "4",
    "4",
    "4",
    "4",
    "4",
    "4",
    "所以，瑞金、会昌、石城、寻乌、安远、广昌、黎川，需要提高自身的经济发展水平，为赣南原中央苏区区域的物流发展提供动力。\n",
    "所以，石城、寻乌、于都、安远、广昌、黎川、上犹、崇义应该重视软硬件环境的营造，完善物流发展硬件条件，加快信息化发展，推动区域物流更快发展。\n",
    "所以，这九个城市应该在不断提高物流产业质量水平的目标下，逐渐扩大物流产业规模，以期使物流竞争力处于上游水平，促进赣南原中央苏区区域流竞争力的提高。\n",
    "3",
    "4",
    "3",
    "3",
    "4",
    "3",
    "3",
    "4",
    "3",
    "4",
    "3",
    "4",
    "4",
    "4",
    "3",
    "4",
    "4",
    "4",
    "4",
    "4",
    "4",
    "4",
    "4",
    "4",
    "4",
    "4",
    "4",
    "4",
    "4",
    "4",
    "3",
    "3",
    "3",
    "4",
    "3",
    "4",
    "4",
    "4",
    "4",
    "3",
    "3",
    "3",
    "4",
    "4",
    "4",
    "4",
    "4",
    "4"
  ],
  "样本选择": [],
  "变量选取": [
    "本文以区域物流环境竞争力、区域物流供需竞争力、区域物流产业规模竞争力、区域物流产业质量竞争力作为一级指标；地区生产总值(GDP)、第三产业增加值、第三产业投资、货物运输量、社会消费品总额、邮电业务总额、货物周转量、金融年末存贷款余额、通车里程、住宿餐饮业总额10个指标变量作为二级指标构建了赣南原中央苏区区域物流与区域经济的线性关系，如表4-1。\n",
    "4",
    "4",
    "4",
    "本文收集了赣南原中央苏区区域经济区兴国、瑞金、宁都、会昌、石城、寻乌、于都、信丰、安远、广昌、黎川、上犹、崇义13个城市的相关数据，通过比较分析明确各个城市的物流发展现状，找出其优劣势所在，以期提出建设性的对策促进其发展。本文采用10个指标变量用来实证研究：地区生产总值GDP(X1)（亿元）、第三产业增加值\n",
    "用这10个指标变量代表区域物流的环境竞争力指标、供需竞争力指标、物流产业规模竞争力指标、物流产业质量竞争力指标。\n",
    "数据如表4-2所示。\n",
    "4",
    "3",
    "3",
    "3",
    "4",
    "图 4-1  研究变量的柱状图\n",
    "表4-3  变量之间相关系数表\n",
    "3",
    "4",
    "4",
    "4",
    "4",
    "4",
    "3",
    "3",
    "3",
    "4",
    "3",
    "4"
  ],
  "模型设计": [
    "4",
    "4",
    "4",
    "4",
    "3",
    "3",
    "3",
    "4",
    "3",
    "4",
    "回归分析通过研究解释变量与被解释变量之间的关系而进行线性分析的一种统计学方法。\n",
    "一元线性回归代表着解释变量唯一；多元线性回归代表着解释变量不唯一。\n",
    "前向逐步分析法是多元线性回归分析的一种方法，通过增加解释变量，使已解释变量贡献最大的变量先进入方程。\n",
    "这样可以逐步删除不重要的解释变量，消除多重共线性问题。\n",
    "转量、社会消费品零售总额、通车里程、邮电总额、第三产业投资、住宿餐饮业总额为解释变量，采用前向逐步回归法，在SPSS软件计算下，得出结果（表4-4~表4-6）。\n",
    "3",
    "4",
    "3",
    "4",
    "4",
    "4",
    "3",
    "4",
    "4",
    "三产业增加值）.302 X 4（通车里程）t值（9.266）（-2.743）（此处通车里程未通过t检验，因而剔除）；\n",
    "4",
    "4",
    "4",
    "4",
    "4",
    "4",
    "4",
    "4",
    "4",
    "4",
    "4",
    "4",
    "4",
    "4",
    "4",
    "4",
    "4",
    "3",
    "3",
    "3",
    "4",
    "3",
    "4",
    "3",
    "4",
    "3",
    "4",
    "4",
    "4",
    "3",
    "4",
    "4",
    "4",
    "4",
    "4",
    "4",
    "4",
    "4",
    "4",
    "4",
    "4",
    "4",
    "4",
    "4",
    "4"
  ],
  "实证分析": [
    "对区域总体来看，总体效率平均值达到0.785，说明赣南苏区区域物流的物流效率处于中等水平，还有极高的发展空间。\n",
    "纯技术效率的平均值0.930，赣南苏区区域纯技术效率较高。\n",
    "采用SPSS统计软件中的因子分析法对各城市的物流竞争力进行了得分排名以及提出对策建议。\n",
    "3",
    "4",
    "3",
    "3",
    "4",
    "3",
    "因子分析法的检验\n",
    "3",
    "4",
    "总体来说，区域经济对区域物流的供需要求、产业规模与质量以及物流环境有着密切联系，但根据表4-16只有兴国、宁都、于都、信丰、上犹、崇义的物流经济水平高于赣南原中央苏区区域平均水平，其它七个城市均小于赣南原中央苏区区域平均水平。\n",
    "设区域各地区货运总量为（y）与影响因素（x1, x2, x3…xi）存在线性相关，则可以\n",
    "4",
    "4",
    "4",
    "4",
    "3",
    "3",
    "3",
    "4",
    "3",
    "量\\n相关\n",
    "显著性（单侧）\n",
    "4",
    "在.01水平（单侧）上显著相关在.05水平（单侧）上显著相关\n",
    "（1）在a=0.01置信水平下，GDP、第三产业增加值、周转量、社会消费品零售总额、通车里程与货运总量显著相关；\n",
    "（2）在a=0.01置信水平下，邮电总额、第三产业投资、住宿餐饮业总额与货运总量不显著相关；\n",
    "(1) GDP、第三产业增加值、周转量、社会消费品零售总额、通车里程与货运总量相关系数都在0.65以上相关程度较高。\n",
    "3",
    "4",
    "从表4-4所示的拟合优度来看，第二个模型比第一个有显著的提高，说明第二个模型优于第一个模型\n",
    "3",
    "4",
    "4",
    "4",
    "由表4-5所示的方程显著性检验来看，两个模型都通过方程显著性检验，说明两个模型回归系数都显著不为0，而且两个模型的F统计量观测值都比较大，说明模型构建显著性较强。\n",
    "3",
    "4",
    "4",
    "（3）通过表4-4看出，判定系数R2为0.896，调整系数为0.876，模型的拟合度较好；通过表4-4的方差分析看出，F值43.286，上述方程通过F检验，也表明了上述回归方程的合理性。\n",
    "（4）通过表4-5回归系数表输出的结果看出，回归系数都通过检验，说明进入模型的自变量对因变量的影响比较显著。\n",
    "3",
    "4",
    "3",
    "3",
    "4",
    "3",
    "3",
    "4",
    "4",
    "4",
    "4",
    "4",
    "3",
    "3",
    "3",
    "4",
    "3",
    "4",
    "3",
    "4",
    "3",
    "4",
    "4",
    "4",
    "3",
    "4",
    "4"
  ],
  "结论": [
    "所以，本章通过第三章的分析所出现的问题，提出相对应的一些对策建议。\n",
    "所以，建议赣南苏区区域在大力发展区域经济的同时，应该大力促进区域物流业的发展力度。\n",
    "因此，无论从物流的总体效率还是物流纯技术效率以及规模效率来看，该区域的物流发展存在着极大的发展不平衡现象。\n",
    "所以，区域应该注重交通设施的建设，来加强各个地区在物流与经济之间的交流。\n",
    "因此，区域应该利用自身的特色产品，形成区域特色产品基地，吸引投资来推动赣南苏区区域物流的发展。\n",
    "因此，要拉动区域物流的需求，区域经济的发展与经济结构要不断发展与升级。\n",
    "DEA以及因子分析并提出相关对策建议，以期望对赣南原中央苏区区域物流与经济协调发展进行改善，用来提高区域经济、物流更好发展。\n",
    "因此，赣南原中央苏区应加大对物流业的投资来促进区域物流的尽快发展，进而促进区域经济的发展。\n",
    "利用因子分析对区域各个地区物流竞争力进行分析，从而分析得出区域总体物流竞争力。\n",
    "通过对区域各个地区物流竞争力进行排名可以看出各个地区物流发展的状况明显不同，物流差距很大，从而看出区域各个地区的物流发展存在很大的不平衡。\n",
    "因此，区域在对物流资源进行整合重组中，应当着重照顾物流业发展缓慢落后的地区，充分发挥优势地区带动劣势地区，核心地区发挥辐射带动作用促进区域物流快速发展。\n",
    "本文依据赣南苏区江西区域各地区城市统计数据，在一些研究理论基础上，采用线性回归模型、DEA以及因子分析方法研究该区域物流与区域经济协调发展的关系，并得到浅的研究成果，为赣南苏区江西区域各地区的区域物流与区域经济相互促进发展提供一定依据。但本文只是对区域做了浅层面的研究，还有很多值得探索的问题，这些问题对区域物流与区域经济的发展都有现实的意义：\n",
    "(1)区域各地区都彼此有自己的物流特点，对促进地区经济发展也有不同的优势，如何探索区域不同地区物流与经济协调发展的背后原因，将对整个区域的发展具有重大意义。\n"
  ]
}